coinmarketcapapi/__init__.py
python_coinmarketcap-0.6.dist-info/LICENSE
python_coinmarketcap-0.6.dist-info/METADATA
python_coinmarketcap-0.6.dist-info/WHEEL
python_coinmarketcap-0.6.dist-info/top_level.txt
python_coinmarketcap-0.6.dist-info/RECORD
