Metadata-Version: 2.2
Name: python-coinmarketcap
Version: 0.6
Summary: CoinMarketCap Python API Wrapper
Home-page: https://github.com/rsz44/python-coinmarketcap
Author: Remi SARRAZIN
Author-email: remi.sarrazin@gmx.com
License: MIT
Classifier: Programming Language :: Python :: 3
Classifier: License :: OSI Approved :: MIT License
Classifier: Operating System :: OS Independent
License-File: LICENSE
Requires-Dist: requests>=2.2.0
Dynamic: author
Dynamic: author-email
Dynamic: classifier
Dynamic: description
Dynamic: description-content-type
Dynamic: home-page
Dynamic: license
Dynamic: requires-dist
Dynamic: summary
